pinax/__init__.py
pinax/types/__init__.py
pinax/types/values.py
pinax/types/periods/__init__.py
pinax/types/periods/fields.py
pinax/types/tests/__init__.py
pinax/types/tests/tests.py
pinax_types-2.0.0.dist-info/AUTHORS
pinax_types-2.0.0.dist-info/LICENSE
pinax_types-2.0.0.dist-info/METADATA
pinax_types-2.0.0.dist-info/WHEEL
pinax_types-2.0.0.dist-info/top_level.txt
pinax_types-2.0.0.dist-info/RECORD
